TkZero/Button.py
TkZero/Checkbutton.py
TkZero/Combobox.py
TkZero/Dialog.py
TkZero/Entry.py
TkZero/Frame.py
TkZero/Keybind.py
TkZero/Label.py
TkZero/Labelframe.py
TkZero/Listbox.py
TkZero/MainWindow.py
TkZero/Menu.py
TkZero/Notebook.py
TkZero/Platform.py
TkZero/Progressbar.py
TkZero/Radiobutton.py
TkZero/Scale.py
TkZero/Scrollbar.py
TkZero/Separator.py
TkZero/Spinbox.py
TkZero/Style.py
TkZero/Text.py
TkZero/Tooltip.py
TkZero/Vector.py
TkZero/Window.py
TkZero/__init__.py
TkZero-0.2.0.dist-info/LICENSE
TkZero-0.2.0.dist-info/WHEEL
TkZero-0.2.0.dist-info/METADATA
TkZero-0.2.0.dist-info/RECORD
