Metadata-Version: 2.1
Name: TkZero
Version: 0.2.0
Summary: TkZero - a lightweight and Pythonic wrapper around Tkinter.
Home-page: https://github.com/UnsignedArduino/TkZero
Author: UnsignedArduino
Author-email: UnsignedArduino@outlook.com
Requires-Python: >=3.8
Classifier: License :: OSI Approved :: GNU General Public License v3 or later (GPLv3+)
Requires-Dist: Pillow >=8.2.0
